rest_uploader/__init__.py
rest_uploader/api_token.py
rest_uploader/cli.py
rest_uploader/email_processor.py
rest_uploader/rest_uploader.py
rest_uploader-1.22.0.dist-info/AUTHORS.rst
rest_uploader-1.22.0.dist-info/LICENSE
rest_uploader-1.22.0.dist-info/METADATA
rest_uploader-1.22.0.dist-info/WHEEL
rest_uploader-1.22.0.dist-info/entry_points.txt
rest_uploader-1.22.0.dist-info/top_level.txt
rest_uploader-1.22.0.dist-info/RECORD
