Metadata-Version: 2.1
Name: rest-uploader
Version: 1.22.0
Summary: REST API File Uploader for Joplin
Home-page: https://github.com/kellerjustin/rest-uploader
Author: Justin Keller
Author-email: Justin Keller <kellerjustin@protonmail.com>
License: MIT License
Project-URL: Homepage, https://github.com/cerealkella/rest-uploader
Project-URL: Bug Tracker, https://github.com/cerealkella/rest-uploader/issues
Keywords: rest_uploader,joplin,rest-uploader
Classifier: Programming Language :: Python :: 3
Classifier: License :: OSI Approved :: MIT License
Classifier: Operating System :: OS Independent
Requires-Python: >=3.7
License-File: LICENSE
License-File: AUTHORS.rst
Requires-Dist: watchdog >=3.0.0
Requires-Dist: requests >=2.31.0
Requires-Dist: tabulate >=0.9.0
Requires-Dist: click >=8.1.3
Requires-Dist: img-processor >=0.20.0
